LICENSE
MANIFEST.in
README.md
setup.py
inscribe_Pysher.egg-info/PKG-INFO
inscribe_Pysher.egg-info/SOURCES.txt
inscribe_Pysher.egg-info/dependency_links.txt
inscribe_Pysher.egg-info/requires.txt
inscribe_Pysher.egg-info/top_level.txt
pysher/__init__.py
pysher/channel.py
pysher/connection.py
pysher/pusher.py